aioflo/__init__.py
aioflo/alarm.py
aioflo/api.py
aioflo/const.py
aioflo/device.py
aioflo/errors.py
aioflo/location.py
aioflo/presence.py
aioflo/user.py
aioflo/util/__init__.py
aioflo/water.py
aioflo-2021.11.0.dist-info/LICENSE
aioflo-2021.11.0.dist-info/WHEEL
aioflo-2021.11.0.dist-info/METADATA
aioflo-2021.11.0.dist-info/RECORD
