Metadata-Version: 2.1
Name: aioflo
Version: 2021.11.0
Summary: A Python3, async-friendly library for Flo by Moen Smart Water Detectors
Home-page: https://github.com/bachya/aioflo
License: MIT
Author: Aaron Bach
Author-email: bachya1208@gmail.com
Requires-Python: >=3.6.0,<4.0.0
Classifier: License :: OSI Approved :: MIT License
Classifier: Programming Language :: Python
Classifier: Programming Language :: Python :: 3
Classifier: Programming Language :: Python :: 3.10
Classifier: Programming Language :: Python :: 3.6
Classifier: Programming Language :: Python :: 3.7
Classifier: Programming Language :: Python :: 3.8
Classifier: Programming Language :: Python :: 3.9
Classifier: Programming Language :: Python :: Implementation :: CPython
Classifier: Programming Language :: Python :: Implementation :: PyPy
Requires-Dist: aiohttp (>=3.7.4,<4.0.0)
Project-URL: Repository, https://github.com/bachya/aioflo
